echemdb_ecdata/__init__.py
echemdb_ecdata/url.py
echemdb_ecdata-0.5.1.dist-info/licenses/LICENSE
echemdb_ecdata-0.5.1.dist-info/METADATA
echemdb_ecdata-0.5.1.dist-info/WHEEL
echemdb_ecdata-0.5.1.dist-info/top_level.txt
echemdb_ecdata-0.5.1.dist-info/RECORD
