Metadata-Version: 2.4
Name: echemdb-ecdata
Version: 0.5.1
Summary: a database for published electrochemical data inferred from SVG and raw CSV files.
Classifier: License :: OSI Approved :: GNU General Public License v3 or later (GPLv3+)
Requires-Python: >=3.9
License-File: LICENSE
Requires-Dist: svgdigitizer<0.14.0,>=0.13.0
Dynamic: license-file
